README.md
setup.py
desktopy/__init__.py
desktopy/elements.py
desktopy.egg-info/PKG-INFO
desktopy.egg-info/SOURCES.txt
desktopy.egg-info/dependency_links.txt
desktopy.egg-info/requires.txt
desktopy.egg-info/top_level.txt