Metadata-Version: 2.1
Name: desktopy
Version: 0.0.1
Summary: A Library For Building Desktop Applications and Interfaces that is built on top of tkinter, customtkinter, and other libraries associated.
Home-page: https://github.com/AnmarHani/DesktoPy
Author: Anmar Hani
Author-email: AnmarHaniV1@gmail.com
License: MIT
Keywords: python,desktop,gui,uidevelopment
Classifier: Development Status :: 4 - Beta
Classifier: Intended Audience :: Developers
Classifier: License :: OSI Approved :: MIT License
Classifier: Programming Language :: Python :: 3.8
Classifier: Operating System :: OS Independent
